[{"name":"管理员","age":"12","sex":"M","interst":["book","badminton"],"memberId":null,"id":1589334709354,"updated_at":"2020-06-17 19:22:15"},{"name":"张三","age":"22","sex":"M","interst":["badminton","basketball"],"memberId":null,"id":1589335076016,"created_at":"2020-05-13 09:57:56","updated_at":"2020-05-14 16:18:41"},{"name":"美女","age":"12","sex":"M","interst":["book","basketball"],"table":[],"memberId":null,"id":1592393067970,"created_at":"2020-06-17 19:24:27","updated_at":"2020-06-17 19:54:52"},{"name":"face","age":"11","sex":"M","interst":["badminton"],"memberId":null,"id":1592398478298,"created_at":"2020-06-17 20:54:38"},{"name":"gg","age":null,"sex":"M","interst":["basketball"],"memberId":null,"id":1592398485321,"created_at":"2020-06-17 20:54:45"},{"name":"abc","age":"ss","sex":"F","interst":["basketball","book"],"memberId":null,"id":1592398493117,"created_at":"2020-06-17 20:54:53"},{"name":"34","age":"12","sex":"M","interst":["basketball"],"memberId":null,"id":1592398499544,"created_at":"2020-06-17 20:54:59"},{"name":"bb","age":null,"sex":null,"interst":[],"memberId":null,"id":1592398503087,"created_at":"2020-06-17 20:55:03"},{"name":"cc","age":null,"sex":null,"interst":[],"memberId":null,"id":1592398506985,"created_at":"2020-06-17 20:55:06"},{"name":"nn","age":null,"sex":null,"interst":[],"memberId":null,"id":1592398511701,"created_at":"2020-06-17 20:55:11"},{"name":"44","age":null,"sex":null,"interst":[],"memberId":null,"id":1592398517399,"created_at":"2020-06-17 20:55:17"}]